pyoetl/__init__.py
pyoetl-0.1.2.dist-info/AUTHORS.rst
pyoetl-0.1.2.dist-info/LICENSE.rst
pyoetl-0.1.2.dist-info/METADATA
pyoetl-0.1.2.dist-info/WHEEL
pyoetl-0.1.2.dist-info/entry_points.txt
pyoetl-0.1.2.dist-info/top_level.txt
pyoetl-0.1.2.dist-info/RECORD
