Metadata-Version: 2.1
Name: pyoetl
Version: 0.1.2
Summary: Python interface to OrientDB ETL tool
Home-page: https://github.com/lebedov/pyoetl/
Author: Lev E. Givon
Author-email: lev@columbia.edu
License: BSD
Platform: UNKNOWN
Classifier: Development Status :: 3 - Alpha
Classifier: Environment :: Console
Classifier: Intended Audience :: Developers
Classifier: License :: OSI Approved :: BSD License
Classifier: Operating System :: OS Independent
Classifier: Programming Language :: Python
Classifier: Programming Language :: Python :: 2
Classifier: Programming Language :: Python :: 3
Classifier: Topic :: Software Development
Classifier: Topic :: Database
Requires-Dist: six
